pyoperators/__init__.py
pyoperators/config.py
pyoperators/core.py
pyoperators/fft.py
pyoperators/flags.py
pyoperators/linear.py
pyoperators/memory.py
pyoperators/nonlinear.py
pyoperators/operators_mpi.py
pyoperators/operators_pywt.py
pyoperators/proxy.py
pyoperators/rules.py
pyoperators/warnings.py
pyoperators/iterative/__init__.py
pyoperators/iterative/algorithms.py
pyoperators/iterative/cg.py
pyoperators/iterative/core.py
pyoperators/iterative/criterions.py
pyoperators/iterative/dli.py
pyoperators/iterative/lanczos.py
pyoperators/iterative/linesearch.py
pyoperators/iterative/optimize.py
pyoperators/iterative/stopconditions.py
pyoperators/utils/__init__.py
pyoperators/utils/cythonutils.cpython-310-darwin.so
pyoperators/utils/fake_MPI.py
pyoperators/utils/misc.py
pyoperators/utils/mpi.py
pyoperators/utils/testing.py
pyoperators/utils/ufuncs.cpython-310-darwin.so
pyoperators-0.16.2.dist-info/LICENCE_FR
pyoperators-0.16.2.dist-info/LICENSE
pyoperators-0.16.2.dist-info/METADATA
pyoperators-0.16.2.dist-info/WHEEL
pyoperators-0.16.2.dist-info/top_level.txt
pyoperators-0.16.2.dist-info/RECORD
