Metadata-Version: 2.1
Name: pyoperators
Version: 0.16.2
Summary: Operators and solvers for high-performance computing.
Author-email: Pierre Chanial <pierre.chanial@gmail.com>
Maintainer-email: Pierre Chanial <pierre.chanial@gmail.com>
License: CeCILL-B FREE SOFTWARE LICENSE AGREEMENT
Project-URL: homepage, https://pchanial.github.io/pyoperators
Project-URL: repository, https://github.com/pchanial/pyoperators
Keywords: scientific computing
Classifier: Programming Language :: Python
Classifier: Programming Language :: Python :: 3
Classifier: Programming Language :: Python :: 3.8
Classifier: Programming Language :: Python :: 3.9
Classifier: Programming Language :: Python :: 3.10
Classifier: Programming Language :: Python :: 3.11
Classifier: Programming Language :: C
Classifier: Programming Language :: Cython
Classifier: Development Status :: 5 - Production/Stable
Classifier: Intended Audience :: Science/Research
Classifier: Operating System :: OS Independent
Classifier: Topic :: Scientific/Engineering
Requires-Python: >=3.8
License-File: LICENCE_FR
License-File: LICENSE
Requires-Dist: numexpr (>=2)
Requires-Dist: numpy (>=1.16)
Requires-Dist: scipy (>=0.9)
Provides-Extra: dev
Requires-Dist: pyfftw ; extra == 'dev'
Requires-Dist: mpi4py ; extra == 'dev'
Requires-Dist: pywavelets (>=0.4.0) ; extra == 'dev'
Requires-Dist: pytest ; extra == 'dev'
Requires-Dist: pytest-cov ; extra == 'dev'
Requires-Dist: pytest-mock ; extra == 'dev'
Requires-Dist: setuptools-scm ; extra == 'dev'
Provides-Extra: fft
Requires-Dist: pyfftw ; extra == 'fft'
Provides-Extra: mpi
Requires-Dist: mpi4py ; extra == 'mpi'
Provides-Extra: wavelets
Requires-Dist: pywavelets (>=0.4.0) ; extra == 'wavelets'
